swem/__init__.py
swem/metrics.py
swem/models/__init__.py
swem/models/pooling.py
swem/models/swem.py
swem/models/word_drop_embedding.py
swem/utils/__init__.py
swem/utils/classes.py
swem/utils/torch_utils.py
pytorch_swem-0.3.5.dist-info/LICENSE
pytorch_swem-0.3.5.dist-info/METADATA
pytorch_swem-0.3.5.dist-info/WHEEL
pytorch_swem-0.3.5.dist-info/top_level.txt
pytorch_swem-0.3.5.dist-info/RECORD
