Metadata-Version: 2.1
Name: pytorch-swem
Version: 0.3.5
Summary: Pytorch implementation of the simple word embedding model.
Home-page: https://github.com/schoennenbeck/swem
Author: Sebastian Schönnenbeck
Author-email: schoennenbeck@gmail.com
License: MIT
Project-URL: Documentation, https://pytorch-swem.readthedocs.io/
Platform: UNKNOWN
Requires-Python: >=3.8
License-File: LICENSE
Requires-Dist: torch (>=1)
Provides-Extra: dev
Requires-Dist: black ; extra == 'dev'
Requires-Dist: isort ; extra == 'dev'
Requires-Dist: mypy ; extra == 'dev'
Requires-Dist: pre-commit ; extra == 'dev'
Requires-Dist: pytest ; extra == 'dev'
Requires-Dist: pytest-cov ; extra == 'dev'
Requires-Dist: coveralls ; extra == 'dev'
Requires-Dist: coverage ; extra == 'dev'
Provides-Extra: docs
Requires-Dist: sphinx ; extra == 'docs'
Requires-Dist: myst-parser ; extra == 'docs'
Requires-Dist: nbsphinx ; extra == 'docs'
Requires-Dist: sphinx-rtd-theme ; extra == 'docs'
Requires-Dist: sphinx-autodoc-typehints ; extra == 'docs'
